LICENSE
mlpractice/__init__.py
mlpractice/cli.py
mlpractice/linear_classifier/__init__.py
mlpractice/linear_classifier/linear_classifier.py
mlpractice/rnn_torch/__init__.py
mlpractice/rnn_torch/rnn_torch.py
mlpractice/templates/linear_classifier/linear_classifier.ipynb
mlpractice/templates/rnn_torch/names
mlpractice/templates/rnn_torch/rnn.png
mlpractice/templates/rnn_torch/rnn_torch.ipynb
mlpractice/tests/__init__.py
mlpractice/tests/linear_classifier/__init__.py
mlpractice/tests/linear_classifier/test_cross_entropy_loss.py
mlpractice/tests/linear_classifier/test_l2_regularization.py
mlpractice/tests/linear_classifier/test_linear_softmax.py
mlpractice/tests/linear_classifier/test_softmax.py
mlpractice/tests/linear_classifier/test_softmax_with_cross_entropy.py
mlpractice/tests/rnn_torch/__init__.py
mlpractice/tests/rnn_torch/test_make_token_to_id.py
mlpractice/tests/rnn_torch/test_make_tokens.py
mlpractice-0.0.2.dist-info/entry_points.txt
mlpractice-0.0.2.dist-info/LICENSE
mlpractice-0.0.2.dist-info/WHEEL
mlpractice-0.0.2.dist-info/METADATA
mlpractice-0.0.2.dist-info/RECORD
