Metadata-Version: 2.1
Name: mlpractice
Version: 0.0.2
Summary: MLpractice is a course, in which you will learn about the most effective machine learning techniques,and gain practice implementing them.
Home-page: https://github.com/avalur/mlpractice
License: MIT
Keywords: machinelearning,deeplearning,ml,dl,practice,mlpractice,machine,deep
Author: Vladislav Ushakov
Author-email: uvd2001@mail.ru
Requires-Python: >=3.7,<=3.9
Classifier: License :: OSI Approved :: MIT License
Classifier: Programming Language :: Python :: 3
Classifier: Programming Language :: Python :: 3.7
Classifier: Programming Language :: Python :: 3.8
Classifier: Programming Language :: Python :: 3.9
Requires-Dist: ipython (>=7.30.1,<8.0.0)
Requires-Dist: jupyter (>=1.0.0,<2.0.0)
Requires-Dist: numpy (>=1.21.4,<2.0.0)
Requires-Dist: scipy (>=1.7.2,<2.0.0)
Requires-Dist: torch (>=1.10.0,<2.0.0)
